<?xml version="1.0"?>
<AutomationAttributes xmlns:xsi="http://www.w3.org/2001/XMLSchema-instance" xmlns:xsd="http://www.w3.org/2001/XMLSchema">
  <TrackFXTriggers />
  <SampleTriggers />
  <ExtendedMixes>
    <ExtendedMixAttributes>
      <TrackDescription>The J.B.'s - (It's Not the Express) It's the J.B.'s Monaurail</TrackDescription>
      <FadeLength>10.060589569160998</FadeLength>
      <FadeEnd>61882776</FadeEnd>
      <FadeEndLoop>2</FadeEndLoop>
      <FadeEndVolume>0.512</FadeEndVolume>
      <PowerDownOnEnd>true</PowerDownOnEnd>
      <ExtendedFadeType>Default</ExtendedFadeType>
      <SampleTriggers />
    </ExtendedMixAttributes>
    <ExtendedMixAttributes>
      <TrackDescription>Tosca - Worksong (Uptight Mix)</TrackDescription>
      <FadeLength>19.901133786848071</FadeLength>
      <FadeEnd>63468752</FadeEnd>
      <FadeEndLoop>3</FadeEndLoop>
      <FadeEndVolume>0.312</FadeEndVolume>
      <PowerDownOnEnd>true</PowerDownOnEnd>
      <ExtendedFadeType>Default</ExtendedFadeType>
      <SampleTriggers />
    </ExtendedMixAttributes>
    <ExtendedMixAttributes>
      <TrackDescription>Tosca - Suzuki</TrackDescription>
      <FadeLength>12.782267573696146</FadeLength>
      <FadeEnd>62749992</FadeEnd>
      <FadeEndLoop>2</FadeEndLoop>
      <FadeEndVolume>0.056</FadeEndVolume>
      <PowerDownOnEnd>false</PowerDownOnEnd>
      <ExtendedFadeType>Default</ExtendedFadeType>
      <SampleTriggers />
    </ExtendedMixAttributes>
    <ExtendedMixAttributes>
      <TrackDescription>Charles Wright &amp; The Watts 103rd Street Rhythm Band - Express Yourself</TrackDescription>
      <FadeLength>19.887414965986395</FadeLength>
      <FadeEnd>63381920</FadeEnd>
      <FadeEndLoop>3</FadeEndLoop>
      <FadeEndVolume>0</FadeEndVolume>
      <PowerDownOnEnd>false</PowerDownOnEnd>
      <ExtendedFadeType>Default</ExtendedFadeType>
      <SampleTriggers />
    </ExtendedMixAttributes>
    <ExtendedMixAttributes>
      <TrackDescription>De La Soul - All Good? (feat. Chaka Khan)</TrackDescription>
      <FadeLength>9.961904761904762</FadeLength>
      <FadeEnd>61841000</FadeEnd>
      <FadeEndLoop>2</FadeEndLoop>
      <FadeEndVolume>0.08</FadeEndVolume>
      <PowerDownOnEnd>false</PowerDownOnEnd>
      <ExtendedFadeType>Default</ExtendedFadeType>
      <SampleTriggers />
    </ExtendedMixAttributes>
    <ExtendedMixAttributes>
      <TrackDescription>Al Green - Let's Stay Together</TrackDescription>
      <FadeLength>15.081247165532879</FadeLength>
      <FadeEnd>61828768</FadeEnd>
      <FadeEndLoop>3</FadeEndLoop>
      <FadeEndVolume>0.144</FadeEndVolume>
      <PowerDownOnEnd>false</PowerDownOnEnd>
      <ExtendedFadeType>Default</ExtendedFadeType>
      <SampleTriggers />
    </ExtendedMixAttributes>
    <ExtendedMixAttributes>
      <TrackDescription>Bob James - Nautilus</TrackDescription>
      <FadeLength>15.660340136054423</FadeLength>
      <FadeEnd>61822824</FadeEnd>
      <FadeEndLoop>3</FadeEndLoop>
      <FadeEndVolume>0.08</FadeEndVolume>
      <PowerDownOnEnd>false</PowerDownOnEnd>
      <ExtendedFadeType>Default</ExtendedFadeType>
      <SampleTriggers />
    </ExtendedMixAttributes>
    <ExtendedMixAttributes>
      <TrackDescription>Quannum Projects - I Changed My Mind (Instrumental)</TrackDescription>
      <FadeLength>34.321315192743761</FadeLength>
      <FadeEnd>61847832</FadeEnd>
      <FadeEndLoop>7</FadeEndLoop>
      <FadeEndVolume>0.328</FadeEndVolume>
      <PowerDownOnEnd>true</PowerDownOnEnd>
      <ExtendedFadeType>Default</ExtendedFadeType>
      <SampleTriggers />
    </ExtendedMixAttributes>
  </ExtendedMixes>
  <TrackSamples />
</AutomationAttributes>