<?xml version="1.0"?>
<AutomationAttributes xmlns:xsi="http://www.w3.org/2001/XMLSchema-instance" xmlns:xsd="http://www.w3.org/2001/XMLSchema">
  <TrackFXTriggers />
  <SampleTriggers />
  <ExtendedMixes>
    <ExtendedMixAttributes>
      <TrackDescription>Michael Longo - Like A Thief In The Night</TrackDescription>
      <FadeLength>16.640158730158731</FadeLength>
      <FadeEnd>38932888</FadeEnd>
      <FadeEndLoop>2</FadeEndLoop>
      <FadeEndVolume>0.192</FadeEndVolume>
      <PowerDownOnEnd>false</PowerDownOnEnd>
      <ExtendedFadeType>Default</ExtendedFadeType>
      <SampleTriggers />
    </ExtendedMixAttributes>
    <ExtendedMixAttributes>
      <TrackDescription>Michael Vinner's Incredible Bongo Band - Apache</TrackDescription>
      <FadeLength>16.862290249433105</FadeLength>
      <FadeEnd>38990272</FadeEnd>
      <FadeEndLoop>2</FadeEndLoop>
      <FadeEndVolume>0.44</FadeEndVolume>
      <PowerDownOnEnd>true</PowerDownOnEnd>
      <ExtendedFadeType>Default</ExtendedFadeType>
      <SampleTriggers />
    </ExtendedMixAttributes>
    <ExtendedMixAttributes>
      <TrackDescription>Blue Mitchell - Good Humour Man</TrackDescription>
      <FadeLength>16.923990929705216</FadeLength>
      <FadeEnd>38975024</FadeEnd>
      <FadeEndLoop>2</FadeEndLoop>
      <FadeEndVolume>0.152</FadeEndVolume>
      <PowerDownOnEnd>false</PowerDownOnEnd>
      <ExtendedFadeType>Default</ExtendedFadeType>
      <SampleTriggers />
    </ExtendedMixAttributes>
    <ExtendedMixAttributes>
      <TrackDescription>Ronny Jordan Meets DJ Krush - So What! (Tuff 'n' Smooth Mix)</TrackDescription>
      <FadeLength>8.231</FadeLength>
      <FadeEnd>41817376</FadeEnd>
      <FadeEndLoop>2</FadeEndLoop>
      <FadeEndVolume>1</FadeEndVolume>
      <PowerDownOnEnd>false</PowerDownOnEnd>
      <ExtendedFadeType>PowerDown</ExtendedFadeType>
      <SampleTriggers />
    </ExtendedMixAttributes>
  </ExtendedMixes>
  <TrackSamples />
</AutomationAttributes>