<?xml version="1.0"?>
<AutomationAttributes xmlns:xsi="http://www.w3.org/2001/XMLSchema-instance" xmlns:xsd="http://www.w3.org/2001/XMLSchema">
  <TrackFXTriggers />
  <SampleTriggers />
  <ExtendedMixes>
    <ExtendedMixAttributes>
      <TrackDescription>Dizzy Gillespie - Matrix</TrackDescription>
      <FadeLength>19.503</FadeLength>
      <FadeEnd>32662216</FadeEnd>
      <FadeEndLoop>0</FadeEndLoop>
      <FadeEndVolume>1</FadeEndVolume>
      <PowerDownOnEnd>false</PowerDownOnEnd>
      <ExtendedFadeType>PowerDown</ExtendedFadeType>
      <SampleTriggers />
    </ExtendedMixAttributes>
    <ExtendedMixAttributes>
      <TrackDescription>Jurassic 5 - I Am Somebody (Instrumental)</TrackDescription>
      <FadeLength>19.503</FadeLength>
      <FadeEnd>32662216</FadeEnd>
      <FadeEndLoop>0</FadeEndLoop>
      <FadeEndVolume>1</FadeEndVolume>
      <PowerDownOnEnd>false</PowerDownOnEnd>
      <ExtendedFadeType>PowerDown</ExtendedFadeType>
      <SampleTriggers />
    </ExtendedMixAttributes>
  </ExtendedMixes>
  <TrackSamples />
</AutomationAttributes>