<?xml version="1.0"?>
<AutomationAttributes xmlns:xsi="http://www.w3.org/2001/XMLSchema-instance" xmlns:xsd="http://www.w3.org/2001/XMLSchema">
  <TrackFXTriggers>
    <TrackFXTrigger>
      <Start>54.720657596371879</Start>
      <Length>0.62052154195011866</Length>
      <DelayNotes>0.25</DelayNotes>
    </TrackFXTrigger>
    <TrackFXTrigger>
      <Start>58.56580498866213</Start>
      <Length>1.2601360544217712</Length>
      <DelayNotes>0.125</DelayNotes>
    </TrackFXTrigger>
    <TrackFXTrigger>
      <Start>111.91419501133787</Start>
      <Length>1.2019274376417286</Length>
      <DelayNotes>0.25</DelayNotes>
    </TrackFXTrigger>
  </TrackFXTriggers>
  <SampleTriggers />
  <ExtendedMixes>
    <ExtendedMixAttributes>
      <TrackDescription>The Budos Band - Up From The South</TrackDescription>
      <FadeLength>14.340340136054422</FadeLength>
      <FadeEnd>60027096</FadeEnd>
      <FadeEndLoop>1</FadeEndLoop>
      <FadeEndVolume>0.68</FadeEndVolume>
      <PowerDownOnEnd>true</PowerDownOnEnd>
      <SampleTriggers>
        <SampleTrigger>
          <Start>150.80968253968254</Start>
          <Length>13.519523809523804</Length>
          <DelayNotes>0.0625</DelayNotes>
          <SampleID>Budos Band - Up From The South - Fade In</SampleID>
        </SampleTrigger>
      </SampleTriggers>
    </ExtendedMixAttributes>
    <ExtendedMixAttributes>
      <TrackDescription>A Tribe Called Quest - Jam</TrackDescription>
      <FadeLength>19.957551020408165</FadeLength>
      <FadeEnd>61446632</FadeEnd>
      <FadeEndLoop>1</FadeEndLoop>
      <FadeEndVolume>0.056</FadeEndVolume>
      <PowerDownOnEnd>false</PowerDownOnEnd>
      <SampleTriggers />
    </ExtendedMixAttributes>
    <ExtendedMixAttributes>
      <TrackDescription>Mos Def - Mr. Universe</TrackDescription>
      <FadeLength>16.502426303854875</FadeLength>
      <FadeEnd>60271064</FadeEnd>
      <FadeEndLoop>1</FadeEndLoop>
      <FadeEndVolume>0.536</FadeEndVolume>
      <PowerDownOnEnd>true</PowerDownOnEnd>
      <SampleTriggers />
    </ExtendedMixAttributes>
  </ExtendedMixes>
  <TrackSamples />
</AutomationAttributes>