<?xml version="1.0"?>
<AutomationAttributes xmlns:xsi="http://www.w3.org/2001/XMLSchema-instance" xmlns:xsd="http://www.w3.org/2001/XMLSchema">
  <TrackFXTriggers />
  <SampleTriggers />
  <ExtendedMixes>
    <ExtendedMixAttributes>
      <TrackDescription>Jorge Ben - Pulo Pulo</TrackDescription>
      <FadeLength>14.423174603174603</FadeLength>
      <FadeEnd>48527168</FadeEnd>
      <FadeEndLoop>0</FadeEndLoop>
      <FadeEndVolume>0.648</FadeEndVolume>
      <PowerDownOnEnd>false</PowerDownOnEnd>
      <ExtendedFadeType>Default</ExtendedFadeType>
      <SampleTriggers />
    </ExtendedMixAttributes>
  </ExtendedMixes>
  <TrackSamples />
</AutomationAttributes>