<?xml version="1.0"?>
<AutomationAttributes xmlns:xsi="http://www.w3.org/2001/XMLSchema-instance" xmlns:xsd="http://www.w3.org/2001/XMLSchema">
  <TrackFXTriggers />
  <SampleTriggers />
  <ExtendedMixes>
    <ExtendedMixAttributes>
      <TrackDescription>King Tubby - The Battle Axe Dub</TrackDescription>
      <FadeLength>16.511156462585035</FadeLength>
      <FadeEnd>78419368</FadeEnd>
      <FadeEndLoop>0</FadeEndLoop>
      <FadeEndVolume>0</FadeEndVolume>
      <PowerDownOnEnd>false</PowerDownOnEnd>
      <SampleTriggers />
    </ExtendedMixAttributes>
  </ExtendedMixes>
  <TrackSamples />
</AutomationAttributes>