<?xml version="1.0"?>
<AutomationAttributes xmlns:xsi="http://www.w3.org/2001/XMLSchema-instance" xmlns:xsd="http://www.w3.org/2001/XMLSchema">
  <TrackFXTriggers />
  <SampleTriggers />
  <ExtendedMixes>
    <ExtendedMixAttributes>
      <TrackDescription>Jean Knight - Mr. Big Stuff</TrackDescription>
      <FadeLength>21.139569160997734</FadeLength>
      <FadeEnd>48783768</FadeEnd>
      <FadeEndLoop>0</FadeEndLoop>
      <FadeEndVolume>0.224</FadeEndVolume>
      <PowerDownOnEnd>true</PowerDownOnEnd>
      <ExtendedFadeType>Default</ExtendedFadeType>
      <SampleTriggers />
    </ExtendedMixAttributes>
    <ExtendedMixAttributes>
      <TrackDescription>The New Mastersounds - Can't Hold Me Down</TrackDescription>
      <FadeLength>21.28265306122449</FadeLength>
      <FadeEnd>48749728</FadeEnd>
      <FadeEndLoop>0</FadeEndLoop>
      <FadeEndVolume>0.376</FadeEndVolume>
      <PowerDownOnEnd>false</PowerDownOnEnd>
      <ExtendedFadeType>Default</ExtendedFadeType>
      <SampleTriggers />
    </ExtendedMixAttributes>
    <ExtendedMixAttributes>
      <TrackDescription>Jurassic 5 - Lausd (Instrumental)</TrackDescription>
      <FadeLength>10.242698412698413</FadeLength>
      <FadeEnd>44971064</FadeEnd>
      <FadeEndLoop>0</FadeEndLoop>
      <FadeEndVolume>0.8</FadeEndVolume>
      <PowerDownOnEnd>true</PowerDownOnEnd>
      <ExtendedFadeType>Default</ExtendedFadeType>
      <SampleTriggers />
    </ExtendedMixAttributes>
    <ExtendedMixAttributes>
      <TrackDescription>Nightmares On Wax - 195lbs</TrackDescription>
      <FadeLength>10.800476190476191</FadeLength>
      <FadeEnd>45013592</FadeEnd>
      <FadeEndLoop>0</FadeEndLoop>
      <FadeEndVolume>0.728</FadeEndVolume>
      <PowerDownOnEnd>true</PowerDownOnEnd>
      <ExtendedFadeType>Default</ExtendedFadeType>
      <SampleTriggers />
    </ExtendedMixAttributes>
    <ExtendedMixAttributes>
      <TrackDescription>A Tribe Called Quest - Oh My God</TrackDescription>
      <FadeLength>20.362448979591836</FadeLength>
      <FadeEnd>48699656</FadeEnd>
      <FadeEndLoop>0</FadeEndLoop>
      <FadeEndVolume>0.488</FadeEndVolume>
      <PowerDownOnEnd>true</PowerDownOnEnd>
      <ExtendedFadeType>Default</ExtendedFadeType>
      <SampleTriggers />
    </ExtendedMixAttributes>
    <ExtendedMixAttributes>
      <TrackDescription>Aretha Franklin - One Step Ahead (Ms. Fat Booty Blend)</TrackDescription>
      <FadeLength>10.781315192743763</FadeLength>
      <FadeEnd>45007952</FadeEnd>
      <FadeEndLoop>0</FadeEndLoop>
      <FadeEndVolume>0.536</FadeEndVolume>
      <PowerDownOnEnd>true</PowerDownOnEnd>
      <ExtendedFadeType>Default</ExtendedFadeType>
      <SampleTriggers />
    </ExtendedMixAttributes>
    <ExtendedMixAttributes>
      <TrackDescription>Jurassic 5 - If You Only Knew (Instrumental)</TrackDescription>
      <FadeLength>19.279727891156462</FadeLength>
      <FadeEnd>47963640</FadeEnd>
      <FadeEndLoop>0</FadeEndLoop>
      <FadeEndVolume>0.008</FadeEndVolume>
      <PowerDownOnEnd>false</PowerDownOnEnd>
      <ExtendedFadeType>Default</ExtendedFadeType>
      <SampleTriggers />
    </ExtendedMixAttributes>
    <ExtendedMixAttributes>
      <TrackDescription>Nightmares On Wax - 70s 80s</TrackDescription>
      <FadeLength>14.982766439909296</FadeLength>
      <FadeEnd>46273648</FadeEnd>
      <FadeEndLoop>0</FadeEndLoop>
      <FadeEndVolume>0.08</FadeEndVolume>
      <PowerDownOnEnd>false</PowerDownOnEnd>
      <ExtendedFadeType>Default</ExtendedFadeType>
      <SampleTriggers />
    </ExtendedMixAttributes>
    <ExtendedMixAttributes>
      <TrackDescription>Horace Andy - Nice And Easy Dub</TrackDescription>
      <FadeLength>11.161519274376417</FadeLength>
      <FadeEnd>45028576</FadeEnd>
      <FadeEndLoop>0</FadeEndLoop>
      <FadeEndVolume>0.608</FadeEndVolume>
      <PowerDownOnEnd>false</PowerDownOnEnd>
      <ExtendedFadeType>Default</ExtendedFadeType>
      <SampleTriggers />
    </ExtendedMixAttributes>
    <ExtendedMixAttributes>
      <TrackDescription>Snoop Dogg - Vapors (Instrumental)</TrackDescription>
      <FadeLength>10.701269841269841</FadeLength>
      <FadeEnd>44951240</FadeEnd>
      <FadeEndLoop>0</FadeEndLoop>
      <FadeEndVolume>0.7760001</FadeEndVolume>
      <PowerDownOnEnd>true</PowerDownOnEnd>
      <ExtendedFadeType>Default</ExtendedFadeType>
      <SampleTriggers />
    </ExtendedMixAttributes>
  </ExtendedMixes>
  <TrackSamples />
</AutomationAttributes>